[
  {
    "zkratka": "XAP",
    "nazev": "Aplikovaná statistika a plánování experimentu",
    "kredity": "3",
    "povinnost": "Povinný",
    "zakonceni": "zá,zk",
    "skupina": "",
    "url": "https://www.vut.cz/studenti/predmety/detail/292407",
    "semestr": [
      "zimní"
    ],
    "rocnik": "1"
  },
  {
    "zkratka": "XEV",
    "nazev": "Evropské právo a dozor nad trhem",
    "kredity": "3",
    "povinnost": "Povinný",
    "zakonceni": "zk",
    "skupina": "",
    "url": "https://www.vut.cz/studenti/predmety/detail/292413",
    "semestr": [
      "zimní"
    ],
    "rocnik": "1"
  },
  {
    "zkratka": "GRI",
    "nazev": "Management kvality",
    "kredity": "4",
    "povinnost": "Povinný",
    "zakonceni": "zá,zk",
    "skupina": "",
    "url": "https://www.vut.cz/studenti/predmety/detail/291827",
    "semestr": [
      "zimní"
    ],
    "rocnik": "1"
  },
  {
    "zkratka": "GMR",
    "nazev": "Management rizik u strojních a elektrických zařízení",
    "kredity": "4",
    "povinnost": "Povinný",
    "zakonceni": "zá,zk",
    "skupina": "",
    "url": "https://www.vut.cz/studenti/predmety/detail/291814",
    "semestr": [
      "zimní"
    ],
    "rocnik": "1"
  },
  {
    "zkratka": "GV0-A",
    "nazev": "Manufacturing Machines Technology",
    "kredity": "4",
    "povinnost": "Povinný",
    "zakonceni": "kl",
    "skupina": "",
    "url": "https://www.vut.cz/studenti/predmety/detail/291842",
    "semestr": [
      "zimní"
    ],
    "rocnik": "1"
  },
  {
    "zkratka": "XPT",
    "nazev": "Praktická metrologie",
    "kredity": "5",
    "povinnost": "Povinný",
    "zakonceni": "zá,zk",
    "skupina": "",
    "url": "https://www.vut.cz/studenti/predmety/detail/292417",
    "semestr": [
      "zimní"
    ],
    "rocnik": "1"
  },
  {
    "zkratka": "PMT",
    "nazev": "Produktový managment, technologie a kvalita",
    "kredity": "3",
    "povinnost": "Povinný",
    "zakonceni": "kl",
    "skupina": "",
    "url": "https://www.vut.cz/studenti/predmety/detail/296031",
    "semestr": [
      "zimní"
    ],
    "rocnik": "1"
  },
  {
    "zkratka": "G1S",
    "nazev": "Stavba výrobních strojů I",
    "kredity": "5",
    "povinnost": "Povinný",
    "zakonceni": "zk",
    "skupina": "",
    "url": "https://www.vut.cz/studenti/predmety/detail/291846",
    "semestr": [
      "zimní"
    ],
    "rocnik": "1"
  },
  {
    "zkratka": "XMT",
    "nazev": "Měřicí technika",
    "kredity": "4",
    "povinnost": "Povinný",
    "zakonceni": "kl",
    "skupina": "",
    "url": "https://www.vut.cz/studenti/predmety/detail/292416",
    "semestr": [
      "letní"
    ],
    "rocnik": "1"
  },
  {
    "zkratka": "XAM",
    "nazev": "Pokročilé metody managementu rizik",
    "kredity": "5",
    "povinnost": "Povinný",
    "zakonceni": "zá,zk",
    "skupina": "",
    "url": "https://www.vut.cz/studenti/predmety/detail/292406",
    "semestr": [
      "letní"
    ],
    "rocnik": "1"
  },
  {
    "zkratka": "XS1",
    "nazev": "Spolehlivost a údržba technických systémů",
    "kredity": "6",
    "povinnost": "Povinný",
    "zakonceni": "zá,zk",
    "skupina": "",
    "url": "https://www.vut.cz/studenti/predmety/detail/292420",
    "semestr": [
      "letní"
    ],
    "rocnik": "1"
  },
  {
    "zkratka": "XRP",
    "nazev": "Statistické řízení procesů",
    "kredity": "5",
    "povinnost": "Povinný",
    "zakonceni": "zá,zk",
    "skupina": "",
    "url": "https://www.vut.cz/studenti/predmety/detail/292419",
    "semestr": [
      "letní"
    ],
    "rocnik": "1"
  },
  {
    "zkratka": "XT1",
    "nazev": "Technická diagnostika I",
    "kredity": "5",
    "povinnost": "Povinný",
    "zakonceni": "zá,zk",
    "skupina": "",
    "url": "https://www.vut.cz/studenti/predmety/detail/292422",
    "semestr": [
      "letní"
    ],
    "rocnik": "1"
  },
  {
    "zkratka": "GSZ",
    "nazev": "Zpracování dat",
    "kredity": "4",
    "povinnost": "Povinný",
    "zakonceni": "zá,zk",
    "skupina": "",
    "url": "https://www.vut.cz/studenti/predmety/detail/291835",
    "semestr": [
      "letní"
    ],
    "rocnik": "1"
  },
  {
    "zkratka": "0PPX",
    "nazev": "Průmyslový projekt (N-KSB)",
    "kredity": "3",
    "povinnost": "Volitelný",
    "zakonceni": "kl",
    "skupina": "",
    "url": "https://www.vut.cz/studenti/predmety/detail/292538",
    "semestr": [
      "letní"
    ],
    "rocnik": "1"
  },
  {
    "zkratka": "GA0",
    "nazev": "Analýza příčin poruch",
    "kredity": "3",
    "povinnost": "Povinný",
    "zakonceni": "zk",
    "skupina": "",
    "url": "https://www.vut.cz/studenti/predmety/detail/291782",
    "semestr": [
      "zimní"
    ],
    "rocnik": "2"
  },
  {
    "zkratka": "XD4",
    "nazev": "Diplomový projekt (M-KSB) I",
    "kredity": "2",
    "povinnost": "Povinný",
    "zakonceni": "zá",
    "skupina": "",
    "url": "https://www.vut.cz/studenti/predmety/detail/292410",
    "semestr": [
      "zimní"
    ],
    "rocnik": "2"
  },
  {
    "zkratka": "5EM",
    "nazev": "Ekonomika a management podniku",
    "kredity": "4",
    "povinnost": "Povinný",
    "zakonceni": "kl",
    "skupina": "",
    "url": "https://www.vut.cz/studenti/predmety/detail/292608",
    "semestr": [
      "zimní"
    ],
    "rocnik": "2"
  },
  {
    "zkratka": "XFB",
    "nazev": "Funkční bezpečnost",
    "kredity": "6",
    "povinnost": "Povinný",
    "zakonceni": "zá,zk",
    "skupina": "",
    "url": "https://www.vut.cz/studenti/predmety/detail/292414",
    "semestr": [
      "zimní"
    ],
    "rocnik": "2"
  },
  {
    "zkratka": "XBA",
    "nazev": "Pokročilé metody bezpečnostních analýz",
    "kredity": "4",
    "povinnost": "Povinný",
    "zakonceni": "kl",
    "skupina": "",
    "url": "https://www.vut.cz/studenti/predmety/detail/292408",
    "semestr": [
      "zimní"
    ],
    "rocnik": "2"
  },
  {
    "zkratka": "GPN",
    "nazev": "Projektový management",
    "kredity": "4",
    "povinnost": "Povinný",
    "zakonceni": "kl",
    "skupina": "",
    "url": "https://www.vut.cz/studenti/predmety/detail/291824",
    "semestr": [
      "zimní"
    ],
    "rocnik": "2"
  },
  {
    "zkratka": "XT2",
    "nazev": "Technická diagnostika II",
    "kredity": "6",
    "povinnost": "Povinný",
    "zakonceni": "zá,zk",
    "skupina": "",
    "url": "https://www.vut.cz/studenti/predmety/detail/292423",
    "semestr": [
      "zimní"
    ],
    "rocnik": "2"
  },
  {
    "zkratka": "GTA",
    "nazev": "Teorie a stavba výrobních systémů",
    "kredity": "4",
    "povinnost": "Povinný",
    "zakonceni": "zá,zk",
    "skupina": "",
    "url": "https://www.vut.cz/studenti/predmety/detail/291836",
    "semestr": [
      "zimní"
    ],
    "rocnik": "2"
  },
  {
    "zkratka": "XZK",
    "nazev": "Zkušebnictví",
    "kredity": "4",
    "povinnost": "Povinný",
    "zakonceni": "kl",
    "skupina": "",
    "url": "https://www.vut.cz/studenti/predmety/detail/292424",
    "semestr": [
      "zimní"
    ],
    "rocnik": "2"
  },
  {
    "zkratka": "0ZC",
    "nazev": "Odborné zdroje a citování",
    "kredity": "2",
    "povinnost": "Volitelný",
    "zakonceni": "zá",
    "skupina": "",
    "url": "https://www.vut.cz/studenti/predmety/detail/292556",
    "semestr": [
      "zimní"
    ],
    "rocnik": "2"
  },
  {
    "zkratka": "XD7",
    "nazev": "Diplomový projekt (M-KSB)",
    "kredity": "11",
    "povinnost": "Povinný",
    "zakonceni": "zá",
    "skupina": "",
    "url": "https://www.vut.cz/studenti/predmety/detail/292411",
    "semestr": [
      "letní"
    ],
    "rocnik": "2"
  },
  {
    "zkratka": "XMI",
    "nazev": "Management bezpečnosti",
    "kredity": "2",
    "povinnost": "Povinný",
    "zakonceni": "kl",
    "skupina": "",
    "url": "https://www.vut.cz/studenti/predmety/detail/292415",
    "semestr": [
      "letní"
    ],
    "rocnik": "2"
  },
  {
    "zkratka": "XRI",
    "nazev": "Management kvality II",
    "kredity": "3",
    "povinnost": "Povinný",
    "zakonceni": "zá,zk",
    "skupina": "",
    "url": "https://www.vut.cz/studenti/predmety/detail/292418",
    "semestr": [
      "letní"
    ],
    "rocnik": "2"
  },
  {
    "zkratka": "XD8",
    "nazev": "Seminář k diplomové práci (M-KSB)",
    "kredity": "3",
    "povinnost": "Povinný",
    "zakonceni": "zá",
    "skupina": "",
    "url": "https://www.vut.cz/studenti/predmety/detail/292412",
    "semestr": [
      "letní"
    ],
    "rocnik": "2"
  },
  {
    "zkratka": "XTM",
    "nazev": "Techniky motivace",
    "kredity": "2",
    "povinnost": "Povinný",
    "zakonceni": "kl",
    "skupina": "",
    "url": "https://www.vut.cz/studenti/predmety/detail/292421",
    "semestr": [
      "letní"
    ],
    "rocnik": "2"
  },
  {
    "zkratka": "GTC",
    "nazev": "Technologičnost konstrukce a oprav (retrofitting) VS",
    "kredity": "2",
    "povinnost": "Povinný",
    "zakonceni": "zk",
    "skupina": "",
    "url": "https://www.vut.cz/studenti/predmety/detail/291837",
    "semestr": [
      "letní"
    ],
    "rocnik": "2"
  },
  {
    "zkratka": "GMB",
    "nazev": "Senzorika řídících a měřících obvodů",
    "kredity": "5",
    "povinnost": "Volitelný",
    "zakonceni": "zá,zk",
    "skupina": "",
    "url": "https://www.vut.cz/studenti/predmety/detail/291808",
    "semestr": [
      "letní"
    ],
    "rocnik": "2"
  }
]