[
  {
    "zkratka": "ZM1",
    "nazev": "CAD modelování",
    "kredity": "4",
    "povinnost": "Povinný",
    "zakonceni": "kl",
    "skupina": "",
    "url": "https://www.vut.cz/studenti/predmety/detail/292466",
    "semestr": [
      "zimní"
    ],
    "rocnik": "1"
  },
  {
    "zkratka": "ZD1",
    "nazev": "Diplomový projekt - koncept",
    "kredity": "5",
    "povinnost": "Povinný",
    "zakonceni": "kl",
    "skupina": "",
    "url": "https://www.vut.cz/studenti/predmety/detail/292456",
    "semestr": [
      "zimní"
    ],
    "rocnik": "1"
  },
  {
    "zkratka": "YE1",
    "nazev": "Projekt design koncept",
    "kredity": "10",
    "povinnost": "Povinný",
    "zakonceni": "zá,zk",
    "skupina": "",
    "url": "https://www.vut.cz/studenti/predmety/detail/292430",
    "semestr": [
      "zimní"
    ],
    "rocnik": "1"
  },
  {
    "zkratka": "ZRS",
    "nazev": "Řízení projektu",
    "kredity": "3",
    "povinnost": "Povinný",
    "zakonceni": "kl",
    "skupina": "",
    "url": "https://www.vut.cz/studenti/predmety/detail/292474",
    "semestr": [
      "zimní"
    ],
    "rocnik": "1"
  },
  {
    "zkratka": "YSD-A",
    "nazev": "Udržitelný design",
    "kredity": "4",
    "povinnost": "Povinný",
    "zakonceni": "zá,zk",
    "skupina": "",
    "url": "https://www.vut.cz/studenti/predmety/detail/291634",
    "semestr": [
      "zimní"
    ],
    "rocnik": "1"
  },
  {
    "zkratka": "YVC-A",
    "nazev": "Vizuální komunikace",
    "kredity": "4",
    "povinnost": "Povinný",
    "zakonceni": "zá,zk",
    "skupina": "",
    "url": "https://www.vut.cz/studenti/predmety/detail/291639",
    "semestr": [
      "zimní"
    ],
    "rocnik": "1"
  },
  {
    "zkratka": "YKH",
    "nazev": "Kresba hlavy",
    "kredity": "3",
    "povinnost": "Volitelný",
    "zakonceni": "zá",
    "skupina": "",
    "url": "https://www.vut.cz/studenti/predmety/detail/292435",
    "semestr": [
      "zimní"
    ],
    "rocnik": "1"
  },
  {
    "zkratka": "YDK",
    "nazev": "Design, kultura a společnost",
    "kredity": "3",
    "povinnost": "Povinný",
    "zakonceni": "zá,zk",
    "skupina": "",
    "url": "https://www.vut.cz/studenti/predmety/detail/292429",
    "semestr": [
      "letní"
    ],
    "rocnik": "1"
  },
  {
    "zkratka": "ZD2",
    "nazev": "Diplomový projekt - literatura a cíle",
    "kredity": "5",
    "povinnost": "Povinný",
    "zakonceni": "kl",
    "skupina": "",
    "url": "https://www.vut.cz/studenti/predmety/detail/292457",
    "semestr": [
      "letní"
    ],
    "rocnik": "1"
  },
  {
    "zkratka": "ZNV",
    "nazev": "Exponenciální technologie",
    "kredity": "3",
    "povinnost": "Povinný",
    "zakonceni": "kl",
    "skupina": "",
    "url": "https://www.vut.cz/studenti/predmety/detail/292467",
    "semestr": [
      "letní"
    ],
    "rocnik": "1"
  },
  {
    "zkratka": "YMV",
    "nazev": "Materiály a procesy pro výrobu",
    "kredity": "4",
    "povinnost": "Povinný",
    "zakonceni": "zá,zk",
    "skupina": "",
    "url": "https://www.vut.cz/studenti/predmety/detail/292440",
    "semestr": [
      "letní"
    ],
    "rocnik": "1"
  },
  {
    "zkratka": "YMT",
    "nazev": "Multimédia a technologie",
    "kredity": "4",
    "povinnost": "Povinný",
    "zakonceni": "kl",
    "skupina": "",
    "url": "https://www.vut.cz/studenti/predmety/detail/292439",
    "semestr": [
      "letní"
    ],
    "rocnik": "1"
  },
  {
    "zkratka": "YE2",
    "nazev": "Projekt design vývoj",
    "kredity": "11",
    "povinnost": "Povinný",
    "zakonceni": "zá,zk",
    "skupina": "",
    "url": "https://www.vut.cz/studenti/predmety/detail/292431",
    "semestr": [
      "letní"
    ],
    "rocnik": "1"
  },
  {
    "zkratka": "YKF",
    "nazev": "Kresba figury",
    "kredity": "3",
    "povinnost": "Volitelný",
    "zakonceni": "zá",
    "skupina": "",
    "url": "https://www.vut.cz/studenti/predmety/detail/292433",
    "semestr": [
      "letní"
    ],
    "rocnik": "1"
  },
  {
    "zkratka": "ZAT-A",
    "nazev": "Aditivní technologie",
    "kredity": "4",
    "povinnost": "Povinný",
    "zakonceni": "zá,zk",
    "skupina": "",
    "url": "https://www.vut.cz/studenti/predmety/detail/292450",
    "semestr": [
      "zimní"
    ],
    "rocnik": "2"
  },
  {
    "zkratka": "YAE",
    "nazev": "Aplikovaná ergonomie",
    "kredity": "3",
    "povinnost": "Povinný",
    "zakonceni": "kl",
    "skupina": "",
    "url": "https://www.vut.cz/studenti/predmety/detail/292425",
    "semestr": [
      "zimní"
    ],
    "rocnik": "2"
  },
  {
    "zkratka": "ZDP",
    "nazev": "Diplomový projekt - metody a výsledky",
    "kredity": "5",
    "povinnost": "Povinný",
    "zakonceni": "kl",
    "skupina": "",
    "url": "https://www.vut.cz/studenti/predmety/detail/292455",
    "semestr": [
      "zimní"
    ],
    "rocnik": "2"
  },
  {
    "zkratka": "YMM",
    "nazev": "Marketing a management v designu",
    "kredity": "4",
    "povinnost": "Povinný",
    "zakonceni": "zá,zk",
    "skupina": "",
    "url": "https://www.vut.cz/studenti/predmety/detail/292438",
    "semestr": [
      "zimní"
    ],
    "rocnik": "2"
  },
  {
    "zkratka": "YE3",
    "nazev": "Projekt design realizace",
    "kredity": "9",
    "povinnost": "Povinný",
    "zakonceni": "zá,zk",
    "skupina": "",
    "url": "https://www.vut.cz/studenti/predmety/detail/292432",
    "semestr": [
      "zimní"
    ],
    "rocnik": "2"
  },
  {
    "zkratka": "YP1",
    "nazev": "Odborná stáž",
    "kredity": "3",
    "povinnost": "Volitelný",
    "zakonceni": "zá",
    "skupina": "",
    "url": "https://www.vut.cz/studenti/predmety/detail/292444",
    "semestr": [
      "zimní"
    ],
    "rocnik": "2"
  },
  {
    "zkratka": "0ZC",
    "nazev": "Odborné zdroje a citování",
    "kredity": "2",
    "povinnost": "Volitelný",
    "zakonceni": "zá",
    "skupina": "",
    "url": "https://www.vut.cz/studenti/predmety/detail/292556",
    "semestr": [
      "zimní"
    ],
    "rocnik": "2"
  },
  {
    "zkratka": "ZD5",
    "nazev": "Diplomový projekt - výsledky a diskuse",
    "kredity": "24",
    "povinnost": "Povinný",
    "zakonceni": "kl",
    "skupina": "",
    "url": "https://www.vut.cz/studenti/predmety/detail/292458",
    "semestr": [
      "letní"
    ],
    "rocnik": "2"
  },
  {
    "zkratka": "SpmkP",
    "nazev": "Průmyslový marketing pro konstruktéry",
    "kredity": "3",
    "povinnost": "Povinný",
    "zakonceni": "zk",
    "skupina": "",
    "url": "https://www.vut.cz/studenti/predmety/detail/297453",
    "semestr": [
      "letní"
    ],
    "rocnik": "2"
  },
  {
    "zkratka": "YVR",
    "nazev": "Virtuální realita",
    "kredity": "3",
    "povinnost": "Povinný",
    "zakonceni": "kl",
    "skupina": "",
    "url": "https://www.vut.cz/studenti/predmety/detail/292446",
    "semestr": [
      "letní"
    ],
    "rocnik": "2"
  }
]