[
  {
    "zkratka": "BYA002",
    "nazev": "Intermediate Level English (exam)",
    "kredity": "2",
    "povinnost": "Compulsory",
    "zakonceni": "Ex",
    "skupina": "",
    "url": "https://www.vut.cz/en/students/courses/detail/289710",
    "semestr": [
      "zimní"
    ],
    "rocnik": "1"
  },
  {
    "zkratka": "NVB060",
    "nazev": "Economy of Municipalities",
    "kredity": "2",
    "povinnost": "Compulsory",
    "zakonceni": "Cr",
    "skupina": "",
    "url": "https://www.vut.cz/en/students/courses/detail/295931",
    "semestr": [
      "zimní"
    ],
    "rocnik": "1"
  },
  {
    "zkratka": "NGA007",
    "nazev": "Monument Restoration",
    "kredity": "4",
    "povinnost": "Compulsory",
    "zakonceni": "Cr,Ex",
    "skupina": "",
    "url": "https://www.vut.cz/en/students/courses/detail/295930",
    "semestr": [
      "zimní"
    ],
    "rocnik": "1"
  },
  {
    "zkratka": "NHA068",
    "nazev": "Fire Safety of Buildings",
    "kredity": "5",
    "povinnost": "Compulsory",
    "zakonceni": "Cr,Ex",
    "skupina": "",
    "url": "https://www.vut.cz/en/students/courses/detail/295926",
    "semestr": [
      "zimní"
    ],
    "rocnik": "1"
  },
  {
    "zkratka": "NSB020",
    "nazev": "Landscape Restoration and Stability",
    "kredity": "5",
    "povinnost": "Compulsory",
    "zakonceni": "Cr,Ex",
    "skupina": "",
    "url": "https://www.vut.cz/en/students/courses/detail/295739",
    "semestr": [
      "zimní"
    ],
    "rocnik": "1"
  },
  {
    "zkratka": "NHB042",
    "nazev": "Saving and Building Adaptation",
    "kredity": "4",
    "povinnost": "Compulsory",
    "zakonceni": "Cr,Ex",
    "skupina": "",
    "url": "https://www.vut.cz/en/students/courses/detail/289560",
    "semestr": [
      "zimní"
    ],
    "rocnik": "1"
  },
  {
    "zkratka": "NMA017",
    "nazev": "Construction Technology of Urban Roads",
    "kredity": "5",
    "povinnost": "Compulsory",
    "zakonceni": "Cr,Ex",
    "skupina": "",
    "url": "https://www.vut.cz/en/students/courses/detail/295925",
    "semestr": [
      "zimní"
    ],
    "rocnik": "1"
  },
  {
    "zkratka": "NVB058",
    "nazev": "Public Finances",
    "kredity": "3",
    "povinnost": "Compulsory",
    "zakonceni": "GCr",
    "skupina": "",
    "url": "https://www.vut.cz/en/students/courses/detail/295767",
    "semestr": [
      "zimní"
    ],
    "rocnik": "1"
  },
  {
    "zkratka": "NGA008",
    "nazev": "Architecture of Engineering Constructions",
    "kredity": "3",
    "povinnost": "Compulsory",
    "zakonceni": "Cr,Ex",
    "skupina": "",
    "url": "https://www.vut.cz/en/students/courses/detail/295915",
    "semestr": [
      "letní"
    ],
    "rocnik": "1"
  },
  {
    "zkratka": "NTA035",
    "nazev": "Energy Resources",
    "kredity": "4",
    "povinnost": "Compulsory",
    "zakonceni": "Cr,Ex",
    "skupina": "",
    "url": "https://www.vut.cz/en/students/courses/detail/295924",
    "semestr": [
      "letní"
    ],
    "rocnik": "1"
  },
  {
    "zkratka": "NMA018",
    "nazev": "Design of Pavements Regarding Security and Environment",
    "kredity": "2",
    "povinnost": "Compulsory",
    "zakonceni": "Cr,Ex",
    "skupina": "",
    "url": "https://www.vut.cz/en/students/courses/detail/295922",
    "semestr": [
      "letní"
    ],
    "rocnik": "1"
  },
  {
    "zkratka": "NUA015",
    "nazev": "Building design in BIM I.",
    "kredity": "2",
    "povinnost": "Compulsory",
    "zakonceni": "Cr",
    "skupina": "",
    "url": "https://www.vut.cz/en/students/courses/detail/295921",
    "semestr": [
      "letní"
    ],
    "rocnik": "1"
  },
  {
    "zkratka": "NVB047",
    "nazev": "Regional Policy",
    "kredity": "3",
    "povinnost": "Compulsory",
    "zakonceni": "GCr",
    "skupina": "",
    "url": "https://www.vut.cz/en/students/courses/detail/295760",
    "semestr": [
      "letní"
    ],
    "rocnik": "1"
  },
  {
    "zkratka": "NUA016-A",
    "nazev": "Smart Cities",
    "kredity": "4",
    "povinnost": "Compulsory",
    "zakonceni": "Cr,Ex",
    "skupina": "",
    "url": "https://www.vut.cz/en/students/courses/detail/295920",
    "semestr": [
      "letní"
    ],
    "rocnik": "1"
  },
  {
    "zkratka": "NHB046",
    "nazev": "Sustainable Building",
    "kredity": "4",
    "povinnost": "Compulsory",
    "zakonceni": "Cr,Ex",
    "skupina": "",
    "url": "https://www.vut.cz/en/students/courses/detail/289563",
    "semestr": [
      "letní"
    ],
    "rocnik": "1"
  },
  {
    "zkratka": "NUB017",
    "nazev": "Database Systems",
    "kredity": "4",
    "povinnost": "Compulsory-optional",
    "zakonceni": "Cr,Ex",
    "skupina": "5867",
    "url": "https://www.vut.cz/en/students/courses/detail/295919",
    "semestr": [
      "letní"
    ],
    "rocnik": "1"
  },
  {
    "zkratka": "NAB025",
    "nazev": "Operations Research",
    "kredity": "4",
    "povinnost": "Compulsory-optional",
    "zakonceni": "Cr,Ex",
    "skupina": "5867",
    "url": "https://www.vut.cz/en/students/courses/detail/295917",
    "semestr": [
      "letní"
    ],
    "rocnik": "1"
  },
  {
    "zkratka": "NUB018",
    "nazev": "Project management IPMA",
    "kredity": "4",
    "povinnost": "Compulsory-optional",
    "zakonceni": "Cr,Ex",
    "skupina": "5867",
    "url": "https://www.vut.cz/en/students/courses/detail/295918",
    "semestr": [
      "letní"
    ],
    "rocnik": "1"
  },
  {
    "zkratka": "NZB012",
    "nazev": "Ethics in Business",
    "kredity": "2",
    "povinnost": "Compulsory-optional",
    "zakonceni": "Cr",
    "skupina": "5868",
    "url": "https://www.vut.cz/en/students/courses/detail/295751",
    "semestr": [
      "letní"
    ],
    "rocnik": "1"
  },
  {
    "zkratka": "NZB011",
    "nazev": "Pedagogy for Engineers",
    "kredity": "2",
    "povinnost": "Compulsory-optional",
    "zakonceni": "Cr",
    "skupina": "5868",
    "url": "https://www.vut.cz/en/students/courses/detail/295738",
    "semestr": [
      "letní"
    ],
    "rocnik": "1"
  },
  {
    "zkratka": "NYB003",
    "nazev": "English for Municipal Engineers",
    "kredity": "2",
    "povinnost": "Compulsory-optional",
    "zakonceni": "Cr",
    "skupina": "5868",
    "url": "https://www.vut.cz/en/students/courses/detail/295916",
    "semestr": [
      "letní"
    ],
    "rocnik": "1"
  },
  {
    "zkratka": "NZB015",
    "nazev": "Presentation Skills (MI)",
    "kredity": "2",
    "povinnost": "Compulsory-optional",
    "zakonceni": "Cr",
    "skupina": "5868",
    "url": "https://www.vut.cz/en/students/courses/detail/295923",
    "semestr": [
      "letní"
    ],
    "rocnik": "1"
  },
  {
    "zkratka": "NZB014",
    "nazev": "Company Practice Psychology",
    "kredity": "2",
    "povinnost": "Compulsory-optional",
    "zakonceni": "Cr",
    "skupina": "5868",
    "url": "https://www.vut.cz/en/students/courses/detail/289576",
    "semestr": [
      "letní"
    ],
    "rocnik": "1"
  },
  {
    "zkratka": "NIA018",
    "nazev": "Diploma Seminar",
    "kredity": "5",
    "povinnost": "Compulsory",
    "zakonceni": "Cr,Ex",
    "skupina": "",
    "url": "https://www.vut.cz/en/students/courses/detail/295929",
    "semestr": [
      "zimní"
    ],
    "rocnik": "2"
  },
  {
    "zkratka": "NMB013",
    "nazev": "Transportation in cities",
    "kredity": "5",
    "povinnost": "Compulsory",
    "zakonceni": "Cr,Ex",
    "skupina": "",
    "url": "https://www.vut.cz/en/students/courses/detail/295908",
    "semestr": [
      "zimní"
    ],
    "rocnik": "2"
  },
  {
    "zkratka": "NVB057",
    "nazev": "Facility Management",
    "kredity": "3",
    "povinnost": "Compulsory",
    "zakonceni": "Cr,Ex",
    "skupina": "",
    "url": "https://www.vut.cz/en/students/courses/detail/295769",
    "semestr": [
      "zimní"
    ],
    "rocnik": "2"
  },
  {
    "zkratka": "NIB019",
    "nazev": "Practical project of municipal engineering",
    "kredity": "17",
    "povinnost": "Compulsory-optional",
    "zakonceni": "Cr",
    "skupina": "5870",
    "url": "https://www.vut.cz/en/students/courses/detail/295928",
    "semestr": [
      "zimní"
    ],
    "rocnik": "2"
  },
  {
    "zkratka": "NIB020",
    "nazev": "Municipal Engineering Project",
    "kredity": "17",
    "povinnost": "Compulsory-optional",
    "zakonceni": "Cr",
    "skupina": "5870",
    "url": "https://www.vut.cz/en/students/courses/detail/295927",
    "semestr": [
      "zimní"
    ],
    "rocnik": "2"
  }
]